{
  "bind": {
    "method": "POST",
    "url": "https://jzsz.uestc.edu.cn/wxvacation/api/epidemic/login/bindUserInfo",
    "data": {
      "sn": "YOUR-STUDENT-NUMBER",
      "idCard": "YOUR-PASSWORD"
    },
    "description": "[未使用] 将 cookie 绑定给用户"
  },
  "cookie": {
    "method": "POST",
    "url": "https://jzsz.uestc.edu.cn/wxvacation/api/epidemic/login/checkBind",
    "data": {},
    "description": "[未使用] 生成 cookie"
  },
  "returned": {
    "method": "POST",
    "url": "https://jzsz.uestc.edu.cn/wxvacation/api/epidemic/monitorRegisterForReturned",
    "data": {
      "healthCondition": "正常",
      "todayMorningTemperature": "36°C~36.5°C",
      "yesterdayEveningTemperature": "36°C~36.5C",
      "yesterdayMiddayTemperature": "36°C~36.5°C",
      "location": "四川省成都市郫都区银杏大道",
      "healthColor": "绿色"
    },
    "description": "在校学生数据"
  },
  "status": {
    "method": "GET",
    "url": "https://jzsz.uestc.edu.cn/wxvacation/api/epidemic/checkRegisterNew",
    "data": {},
    "description": "查询学生状态"
  },
  "unreturned": {
    "method": "POST",
    "url": "https://jzsz.uestc.edu.cn/wxvacation/api/epidemic/monitorRegister",
    "data": {
      "currentAddress": "甘肃省平凉市华亭市东大街",
      "remark": "",
      "healthInfo": "正常",
      "healthColor": "绿色",
      "isContactWuhan": 0,
      "isFever": 0,
      "isInSchool": 0,
      "isLeaveChengdu": 1,
      "isSymptom": 0,
      "temperature": "36.5°C~36.9°C",
      "province": "甘肃省",
      "city": "平凉市",
      "county": "华亭市"
    },
    "description": "离校学生数据"
  }
}
